[{"Variable":"runtime","Now":338.57,"Min":314.57,"Max":338.57,"Avg":326.57},{"Variable":"adc_vb_f","Now":12.833,"Min":12.109,"Max":13.852,"Avg":12.44},{"Variable":"adc_va_f","Now":16.55,"Min":0.0,"Max":17.252,"Avg":9.83},{"Variable":"adc_vl_f","Now":12.759,"Min":12.088,"Max":13.806,"Avg":12.4},{"Variable":"adc_ic_f","Now":3.81,"Min":0.0,"Max":12.229,"Avg":1.4},{"Variable":"adc_il_f","Now":1.773,"Min":1.573,"Max":2.249,"Avg":1.9},{"Variable":"t_hs","Now":39.0,"Min":22.0,"Max":45.0,"Avg":30.26},{"Variable":"t_batt","Now":39.0,"Min":23.0,"Max":44.0,"Avg":30.76},{"Variable":"t_amb","Now":39.0,"Min":23.0,"Max":44.0,"Avg":30.76},{"Variable":"t_rts","Now":25.0,"Min":25.0,"Max":25.0,"Avg":25.0},{"Variable":"charge_state","Now":5.0,"Min":3.0,"Max":6.0,"Avg":4.23},{"Variable":"array_fault","Now":0.0,"Min":0.0,"Max":0.0,"Avg":0.0},{"Variable":"vb_f","Now":12.839,"Min":12.137,"Max":13.672,"Avg":12.44},{"Variable":"vb_ref","Now":13.411,"Min":0.0,"Max":13.883,"Avg":8.31},{"Variable":"ahc_r","Now":1458.6,"Min":1425.3,"Max":1458.6,"Avg":1435.04},{"Variable":"ahc_t","Now":1458.6,"Min":1425.3,"Max":1458.6,"Avg":1435.04},{"Variable":"kwhc","Now":18.8,"Min":18.4,"Max":18.8,"Avg":18.53},{"Variable":"load_state","Now":1.0,"Min":1.0,"Max":1.0,"Avg":1.0},{"Variable":"load_fault","Now":0.0,"Min":0.0,"Max":0.0,"Avg":0.0},{"Variable":"v_lvd","Now":11.499,"Min":11.469,"Max":11.499,"Avg":11.48},{"Variable":"ahl_r","Now":1391.4,"Min":1346.0,"Max":1391.4,"Avg":1368.9},{"Variable":"ahl_t","Now":1391.4,"Min":1346.0,"Max":1391.4,"Avg":1368.9},{"Variable":"hourmeter","Now":4141.0,"Min":4117.0,"Max":4141.0,"Avg":4128.51},{"Variable":"alarm","Now":1.0,"Min":1.0,"Max":1.0,"Avg":1.0},{"Variable":"dip_switch","Now":13.0,"Min":13.0,"Max":13.0,"Avg":13.0},{"Variable":"led_state","Now":6.0,"Min":5.0,"Max":6.0,"Avg":6.0},{"Variable":"power_out","Now":48.874,"Min":0.0,"Max":165.994,"Avg":18.08},{"Variable":"power_load","Now":22.622,"Min":21.639,"Max":27.276,"Avg":23.49},{"Variable":"power_net","Now":23.452,"Min":-30.061,"Max":141.045,"Avg":-8.21},{"Variable":"sweep_vmp","Now":16.58,"Min":8.292,"Max":17.242,"Avg":12.74},{"Variable":"sweep_pmax","Now":51.592,"Min":3.261,"Max":147.317,"Avg":19.04},{"Variable":"sweep_voc","Now":20.056,"Min":11.057,"Max":21.228,"Avg":15.96},{"Variable":"vb_min_daily","Now":12.103,"Min":12.103,"Max":12.366,"Avg":12.18},{"Variable":"vb_max_daily","Now":13.507,"Min":12.369,"Max":13.956,"Avg":12.95},{"Variable":"ahc_daily","Now":26.5,"Min":0.0,"Max":32.3,"Avg":10.6},{"Variable":"ahl_daily","Now":34.7,"Min":0.0,"Max":44.8,"Avg":22.83},{"Variable":"ahnet_daily","Now":-8.2,"Min":-23.4,"Max":0.0,"Avg":-12.23},{"Variable":"array_fault_daily","Now":0.0,"Min":0.0,"Max":0.0,"Avg":0.0},{"Variable":"load_fault_daily","Now":0.0,"Min":0.0,"Max":0.0,"Avg":0.0},{"Variable":"alarm_daily","Now":1.0,"Min":1.0,"Max":1.0,"Avg":1.0},{"Variable":"vb_min","Now":10.779,"Min":10.779,"Max":10.779,"Avg":10.78},{"Variable":"vb_max","Now":20.898,"Min":20.898,"Max":20.898,"Avg":20.9},{"Variable":"sensor_uptime","Now":342.689,"Min":318.695,"Max":342.689,"Avg":330.69},{"Variable":"ping","Now":0.0,"Min":0.0,"Max":0.0,"Avg":0.0},{"Variable":"crc_errors","Now":2.0,"Min":2.0,"Max":2.0,"Avg":2.0},{"Variable":"crc_errors_delta","Now":0.0,"Min":0.0,"Max":0.0,"Avg":0.0},{"Variable":"crc_errors_hourly","Now":0.0,"Min":0.0,"Max":0.0,"Avg":0.0},{"Variable":"crc_errors_daily","Now":0.0,"Min":0.0,"Max":0.0,"Avg":0.0},{"Variable":"valid_packets","Now":1930.0,"Min":1924.0,"Max":1930.0,"Avg":1927.19},{"Variable":"trigger_delta","Now":0.0,"Min":0.0,"Max":1.0,"Avg":0.0},{"Variable":"trigger_rate_1min","Now":0.0,"Min":0.0,"Max":6.0,"Avg":0.0},{"Variable":"trigger_rate_5min","Now":0.0,"Min":0.0,"Max":1.2,"Avg":0.0},{"Variable":"trigger_rate_1hr","Now":0.0,"Min":0.0,"Max":0.1,"Avg":0.0},{"Variable":"bytes_read","Now":206.78,"Min":195.13,"Max":206.78,"Avg":200.96},{"Variable":"bytes_written","Now":42.46,"Min":42.33,"Max":42.46,"Avg":42.4},{"Variable":"bytes_remaining","Now":277.66,"Min":277.66,"Max":277.79,"Avg":277.72},{"Variable":"triggers_remaining","Now":12621.0,"Min":12621.0,"Max":12627.0,"Avg":12623.81},{"Variable":"packets_sent","Now":0.0,"Min":0.0,"Max":0.0,"Avg":0.0},{"Variable":"packets_dropped","Now":0.0,"Min":0.0,"Max":0.0,"Avg":0.0}]