[{"Variable":"runtime","Now":469.68,"Min":445.7,"Max":469.68,"Avg":457.69},{"Variable":"adc_vb_f","Now":12.027,"Min":11.987,"Max":13.47,"Avg":12.34},{"Variable":"adc_va_f","Now":14.941,"Min":0.0,"Max":17.383,"Avg":9.13},{"Variable":"adc_vl_f","Now":11.975,"Min":11.948,"Max":13.425,"Avg":12.31},{"Variable":"adc_ic_f","Now":0.498,"Min":0.0,"Max":10.453,"Avg":1.54},{"Variable":"adc_il_f","Now":1.964,"Min":0.531,"Max":2.15,"Avg":1.83},{"Variable":"t_hs","Now":30.0,"Min":28.0,"Max":54.0,"Avg":36.48},{"Variable":"t_batt","Now":30.0,"Min":29.0,"Max":52.0,"Avg":36.94},{"Variable":"t_amb","Now":30.0,"Min":29.0,"Max":52.0,"Avg":36.94},{"Variable":"t_rts","Now":25.0,"Min":25.0,"Max":25.0,"Avg":25.0},{"Variable":"charge_state","Now":5.0,"Min":3.0,"Max":5.0,"Avg":4.18},{"Variable":"array_fault","Now":0.0,"Min":0.0,"Max":0.0,"Avg":0.0},{"Variable":"vb_f","Now":12.027,"Min":11.987,"Max":13.431,"Avg":12.34},{"Variable":"vb_ref","Now":13.868,"Min":0.0,"Max":13.898,"Avg":7.87},{"Variable":"ahc_r","Now":1151.6,"Min":1115.3,"Max":1151.6,"Avg":1140.88},{"Variable":"ahc_t","Now":1151.6,"Min":1115.3,"Max":1151.6,"Avg":1140.88},{"Variable":"kwhc","Now":15.0,"Min":14.5,"Max":15.0,"Avg":14.85},{"Variable":"load_state","Now":1.0,"Min":1.0,"Max":1.0,"Avg":1.0},{"Variable":"load_fault","Now":0.0,"Min":0.0,"Max":0.0,"Avg":0.0},{"Variable":"v_lvd","Now":11.478,"Min":11.472,"Max":11.499,"Avg":11.48},{"Variable":"ahl_r","Now":1024.4,"Min":980.6,"Max":1024.4,"Avg":1001.32},{"Variable":"ahl_t","Now":1024.4,"Min":980.6,"Max":1024.4,"Avg":1001.32},{"Variable":"hourmeter","Now":5078.0,"Min":5054.0,"Max":5078.0,"Avg":5065.6},{"Variable":"alarm","Now":1.0,"Min":1.0,"Max":1.0,"Avg":1.0},{"Variable":"dip_switch","Now":13.0,"Min":13.0,"Max":13.0,"Avg":13.0},{"Variable":"led_state","Now":8.0,"Min":6.0,"Max":8.0,"Avg":6.49},{"Variable":"power_out","Now":5.979,"Min":0.0,"Max":138.922,"Avg":19.83},{"Variable":"power_load","Now":23.519,"Min":6.479,"Max":26.881,"Avg":22.56},{"Variable":"power_net","Now":-20.34,"Min":-27.502,"Max":113.745,"Avg":-5.53},{"Variable":"sweep_vmp","Now":14.941,"Min":8.218,"Max":17.404,"Avg":12.24},{"Variable":"sweep_pmax","Now":5.526,"Min":3.276,"Max":137.639,"Avg":21.33},{"Variable":"sweep_voc","Now":18.652,"Min":10.959,"Max":21.118,"Avg":15.56},{"Variable":"vb_min_daily","Now":11.966,"Min":11.966,"Max":12.216,"Avg":12.07},{"Variable":"vb_max_daily","Now":12.216,"Min":12.216,"Max":13.48,"Avg":12.71},{"Variable":"ahc_daily","Now":0.1,"Min":0.0,"Max":36.2,"Avg":9.26},{"Variable":"ahl_daily","Now":21.1,"Min":0.0,"Max":34.8,"Avg":17.19},{"Variable":"ahnet_daily","Now":-21.0,"Min":-21.0,"Max":4.5,"Avg":-7.92},{"Variable":"array_fault_daily","Now":0.0,"Min":0.0,"Max":0.0,"Avg":0.0},{"Variable":"load_fault_daily","Now":0.0,"Min":0.0,"Max":0.0,"Avg":0.0},{"Variable":"alarm_daily","Now":1.0,"Min":1.0,"Max":1.0,"Avg":1.0},{"Variable":"vb_min","Now":10.779,"Min":10.779,"Max":10.779,"Avg":10.78},{"Variable":"vb_max","Now":20.898,"Min":20.898,"Max":20.898,"Avg":20.9},{"Variable":"sensor_uptime","Now":22.499,"Min":0.002,"Max":22.499,"Avg":11.25},{"Variable":"ping","Now":0.0,"Min":0.0,"Max":1.0,"Avg":0.06},{"Variable":"crc_errors","Now":0.0,"Min":0.0,"Max":0.0,"Avg":0.0},{"Variable":"crc_errors_delta","Now":0.0,"Min":0.0,"Max":0.0,"Avg":0.0},{"Variable":"crc_errors_hourly","Now":0.0,"Min":0.0,"Max":0.0,"Avg":0.0},{"Variable":"crc_errors_daily","Now":0.0,"Min":0.0,"Max":0.0,"Avg":0.0},{"Variable":"valid_packets","Now":195.0,"Min":0.0,"Max":195.0,"Avg":126.08},{"Variable":"trigger_delta","Now":0.0,"Min":0.0,"Max":7.0,"Avg":0.14},{"Variable":"trigger_rate_1min","Now":0.0,"Min":0.0,"Max":7.0,"Avg":0.14},{"Variable":"trigger_rate_5min","Now":0.0,"Min":0.0,"Max":5.0,"Avg":0.14},{"Variable":"trigger_rate_1hr","Now":0.033,"Min":0.0,"Max":1.717,"Avg":0.14},{"Variable":"bytes_read","Now":15.07,"Min":0.0,"Max":15.07,"Avg":8.16},{"Variable":"bytes_written","Now":4.29,"Min":0.0,"Max":4.29,"Avg":2.77},{"Variable":"bytes_remaining","Now":36.76,"Min":36.76,"Max":41.05,"Avg":38.28},{"Variable":"triggers_remaining","Now":1671.0,"Min":1671.0,"Max":1866.0,"Avg":1739.92},{"Variable":"packets_sent","Now":0.0,"Min":0.0,"Max":0.0,"Avg":0.0},{"Variable":"packets_dropped","Now":0.0,"Min":0.0,"Max":0.0,"Avg":0.0}]