[{"Variable":"runtime","Now":145.0,"Min":121.0,"Max":145.0,"Avg":133.0},{"Variable":"ping","Now":0.0,"Min":0.0,"Max":2.0,"Avg":0.27},{"Variable":"adc_vb_f","Now":13.901,"Min":11.478,"Max":13.907,"Avg":12.17},{"Variable":"adc_va_f","Now":37.793,"Min":0.555,"Max":38.028,"Avg":14.78},{"Variable":"adc_vl_f","Now":13.76,"Min":0.0,"Max":13.837,"Avg":8.97},{"Variable":"adc_ic_f","Now":7.465,"Min":0.0,"Max":15.0,"Avg":2.69},{"Variable":"adc_il_f","Now":0.73,"Min":0.0,"Max":1.739,"Avg":0.78},{"Variable":"t_hs","Now":39.0,"Min":10.0,"Max":46.0,"Avg":20.49},{"Variable":"t_batt","Now":38.0,"Min":11.0,"Max":41.0,"Avg":20.33},{"Variable":"t_amb","Now":38.0,"Min":11.0,"Max":41.0,"Avg":20.33},{"Variable":"t_rts","Now":25.0,"Min":25.0,"Max":25.0,"Avg":25.0},{"Variable":"charge_state","Now":6.0,"Min":3.0,"Max":6.0,"Avg":4.0},{"Variable":"array_fault","Now":0.0,"Min":0.0,"Max":0.0,"Avg":0.0},{"Variable":"vb_f","Now":13.901,"Min":11.478,"Max":13.907,"Avg":12.16},{"Variable":"vb_ref","Now":13.904,"Min":0.0,"Max":14.728,"Avg":6.27},{"Variable":"ahc_r","Now":153.7,"Min":89.2,"Max":153.7,"Avg":101.74},{"Variable":"ahc_t","Now":153.7,"Min":89.2,"Max":153.7,"Avg":101.74},{"Variable":"kwhc","Now":2.0,"Min":1.2,"Max":2.0,"Avg":1.3},{"Variable":"load_state","Now":1.0,"Min":1.0,"Max":3.0,"Avg":1.54},{"Variable":"load_fault","Now":0.0,"Min":0.0,"Max":0.0,"Avg":0.0},{"Variable":"v_lvd","Now":11.499,"Min":11.481,"Max":11.499,"Avg":11.49},{"Variable":"ahl_r","Now":144.3,"Min":125.7,"Max":144.3,"Avg":136.94},{"Variable":"ahl_t","Now":144.3,"Min":125.7,"Max":144.3,"Avg":136.94},{"Variable":"hourmeter","Now":8397.0,"Min":8373.0,"Max":8397.0,"Avg":8384.65},{"Variable":"alarm","Now":1.0,"Min":1.0,"Max":1000001.0,"Avg":24289.69},{"Variable":"dip_switch","Now":1101.0,"Min":1101.0,"Max":1101.0,"Avg":1101.0},{"Variable":"led_state","Now":5.0,"Min":5.0,"Max":11.0,"Avg":8.75},{"Variable":"power_out","Now":103.606,"Min":0.0,"Max":207.485,"Avg":36.45},{"Variable":"power_load","Now":10.045,"Min":0.0,"Max":19.981,"Avg":9.41},{"Variable":"sweep_vmp","Now":33.456,"Min":7.874,"Max":37.979,"Avg":18.24},{"Variable":"sweep_pmax","Now":195.919,"Min":3.654,"Max":195.919,"Avg":44.11},{"Variable":"sweep_voc","Now":41.821,"Min":10.498,"Max":42.596,"Avg":23.32},{"Variable":"vb_min_daily","Now":11.435,"Min":11.42,"Max":11.798,"Avg":11.49},{"Variable":"vb_max_daily","Now":13.91,"Min":11.801,"Max":13.91,"Avg":12.39},{"Variable":"ahc_daily","Now":58.2,"Min":0.0,"Max":58.2,"Avg":9.36},{"Variable":"ahl_daily","Now":14.1,"Min":0.1,"Max":22.3,"Avg":10.6},{"Variable":"array_fault_daily","Now":0.0,"Min":0.0,"Max":0.0,"Avg":0.0},{"Variable":"load_fault_daily","Now":0.0,"Min":0.0,"Max":0.0,"Avg":0.0},{"Variable":"alarm_daily","Now":1e+19,"Min":1.0,"Max":1e+19,"Avg":6.41e+18},{"Variable":"vb_min","Now":9.439,"Min":9.439,"Max":9.439,"Avg":9.44},{"Variable":"vb_max","Now":19.47,"Min":19.47,"Max":19.47,"Avg":19.47},{"Variable":"sensor_uptime","Now":4.763,"Min":0.003,"Max":11.467,"Avg":4.56},{"Variable":"crc_errors","Now":0.0,"Min":0.0,"Max":0.0,"Avg":0.0},{"Variable":"crc_errors_delta","Now":0.0,"Min":0.0,"Max":0.0,"Avg":0.0},{"Variable":"crc_errors_hourly","Now":0.0,"Min":0.0,"Max":0.0,"Avg":0.0},{"Variable":"crc_errors_daily","Now":0.0,"Min":0.0,"Max":0.0,"Avg":0.0},{"Variable":"valid_packets","Now":11.0,"Min":0.0,"Max":129.0,"Avg":28.15},{"Variable":"trigger_delta","Now":0.0,"Min":0.0,"Max":4.0,"Avg":0.19},{"Variable":"trigger_rate_1min","Now":0.0,"Min":0.0,"Max":4.0,"Avg":0.19},{"Variable":"trigger_rate_5min","Now":0.0,"Min":0.0,"Max":1.6,"Avg":0.19},{"Variable":"trigger_rate_1hr","Now":0.033,"Min":0.0,"Max":0.583,"Avg":0.18},{"Variable":"bytes_read","Now":2.53,"Min":0.0,"Max":8.34,"Avg":2.8},{"Variable":"bytes_written","Now":0.24,"Min":0.0,"Max":2.84,"Avg":0.62},{"Variable":"bytes_remaining","Now":478.18,"Min":478.18,"Max":482.47,"Avg":480.31},{"Variable":"triggers_remaining","Now":21735.0,"Min":21735.0,"Max":21930.0,"Avg":21831.72},{"Variable":"packets_sent","Now":0.0,"Min":0.0,"Max":0.0,"Avg":0.0},{"Variable":"packets_dropped","Now":0.0,"Min":0.0,"Max":0.0,"Avg":0.0}]