[{"Variable":"runtime","Now":103.06,"Min":79.07,"Max":103.06,"Avg":91.07},{"Variable":"adc_vb_f","Now":12.329,"Min":12.057,"Max":13.205,"Avg":12.4},{"Variable":"adc_va_f","Now":13.406,"Min":0.0,"Max":17.825,"Avg":9.6},{"Variable":"adc_vl_f","Now":12.289,"Min":12.012,"Max":13.196,"Avg":12.36},{"Variable":"adc_ic_f","Now":0.188,"Min":0.0,"Max":10.327,"Avg":2.11},{"Variable":"adc_il_f","Now":1.95,"Min":1.679,"Max":2.394,"Avg":1.88},{"Variable":"t_hs","Now":37.0,"Min":26.0,"Max":56.0,"Avg":36.78},{"Variable":"t_batt","Now":38.0,"Min":27.0,"Max":54.0,"Avg":37.16},{"Variable":"t_amb","Now":38.0,"Min":27.0,"Max":54.0,"Avg":37.16},{"Variable":"t_rts","Now":25.0,"Min":25.0,"Max":25.0,"Avg":25.0},{"Variable":"charge_state","Now":5.0,"Min":1.0,"Max":6.0,"Avg":4.23},{"Variable":"array_fault","Now":0.0,"Min":0.0,"Max":0.0,"Avg":0.0},{"Variable":"vb_f","Now":12.329,"Min":12.064,"Max":13.162,"Avg":12.4},{"Variable":"vb_ref","Now":13.44,"Min":0.0,"Max":13.765,"Avg":8.21},{"Variable":"ahc_r","Now":986.3,"Min":936.1,"Max":986.3,"Avg":949.41},{"Variable":"ahc_t","Now":986.3,"Min":936.1,"Max":986.3,"Avg":949.41},{"Variable":"kwhc","Now":12.7,"Min":12.1,"Max":12.7,"Avg":12.26},{"Variable":"load_state","Now":1.0,"Min":1.0,"Max":1.0,"Avg":1.0},{"Variable":"load_fault","Now":0.0,"Min":0.0,"Max":0.0,"Avg":0.0},{"Variable":"v_lvd","Now":11.475,"Min":11.472,"Max":11.499,"Avg":11.48},{"Variable":"ahl_r","Now":948.2,"Min":903.2,"Max":948.2,"Avg":925.97},{"Variable":"ahl_t","Now":948.2,"Min":903.2,"Max":948.2,"Avg":925.97},{"Variable":"hourmeter","Now":3905.0,"Min":3881.0,"Max":3905.0,"Avg":3892.97},{"Variable":"alarm","Now":1.0,"Min":1.0,"Max":1.0,"Avg":1.0},{"Variable":"dip_switch","Now":13.0,"Min":13.0,"Max":13.0,"Avg":13.0},{"Variable":"led_state","Now":6.0,"Min":5.0,"Max":8.0,"Avg":7.56},{"Variable":"power_out","Now":2.31,"Min":0.0,"Max":133.653,"Avg":26.99},{"Variable":"power_load","Now":23.964,"Min":21.192,"Max":31.167,"Avg":23.21},{"Variable":"power_net","Now":-24.454,"Min":-27.295,"Max":108.433,"Avg":0.98},{"Variable":"sweep_vmp","Now":13.031,"Min":8.136,"Max":17.862,"Avg":12.45},{"Variable":"sweep_pmax","Now":3.156,"Min":3.156,"Max":128.549,"Avg":28.78},{"Variable":"sweep_voc","Now":17.371,"Min":10.849,"Max":20.483,"Avg":15.83},{"Variable":"vb_min_daily","Now":12.048,"Min":11.981,"Max":12.274,"Avg":12.09},{"Variable":"vb_max_daily","Now":13.205,"Min":12.277,"Max":13.205,"Avg":12.64},{"Variable":"ahc_daily","Now":50.2,"Min":0.0,"Max":56.3,"Avg":16.04},{"Variable":"ahl_daily","Now":42.8,"Min":0.0,"Max":45.5,"Avg":22.78},{"Variable":"ahnet_daily","Now":7.4,"Min":-22.6,"Max":13.0,"Avg":-6.74},{"Variable":"array_fault_daily","Now":0.0,"Min":0.0,"Max":0.0,"Avg":0.0},{"Variable":"load_fault_daily","Now":0.0,"Min":0.0,"Max":0.0,"Avg":0.0},{"Variable":"alarm_daily","Now":1.0,"Min":1.0,"Max":1.0,"Avg":1.0},{"Variable":"vb_min","Now":10.779,"Min":10.779,"Max":10.779,"Avg":10.78},{"Variable":"vb_max","Now":20.898,"Min":20.898,"Max":20.898,"Avg":20.9},{"Variable":"sensor_uptime","Now":107.221,"Min":83.228,"Max":107.221,"Avg":95.22},{"Variable":"ping","Now":0.0,"Min":0.0,"Max":0.0,"Avg":0.0},{"Variable":"crc_errors","Now":2.0,"Min":2.0,"Max":2.0,"Avg":2.0},{"Variable":"crc_errors_delta","Now":0.0,"Min":0.0,"Max":0.0,"Avg":0.0},{"Variable":"crc_errors_hourly","Now":0.0,"Min":0.0,"Max":0.0,"Avg":0.0},{"Variable":"crc_errors_daily","Now":0.0,"Min":0.0,"Max":0.0,"Avg":0.0},{"Variable":"valid_packets","Now":1470.0,"Min":1462.0,"Max":1470.0,"Avg":1465.51},{"Variable":"trigger_delta","Now":0.0,"Min":0.0,"Max":1.0,"Avg":0.0},{"Variable":"trigger_rate_1min","Now":0.0,"Min":0.0,"Max":6.0,"Avg":0.01},{"Variable":"trigger_rate_5min","Now":0.0,"Min":0.0,"Max":1.2,"Avg":0.01},{"Variable":"trigger_rate_1hr","Now":0.0,"Min":0.0,"Max":0.2,"Avg":0.01},{"Variable":"bytes_read","Now":83.68,"Min":71.99,"Max":83.68,"Avg":77.83},{"Variable":"bytes_written","Now":32.34,"Min":32.16,"Max":32.34,"Avg":32.24},{"Variable":"bytes_remaining","Now":287.78,"Min":287.78,"Max":287.96,"Avg":287.88},{"Variable":"triggers_remaining","Now":13081.0,"Min":13081.0,"Max":13089.0,"Avg":13085.49},{"Variable":"packets_sent","Now":0.0,"Min":0.0,"Max":0.0,"Avg":0.0},{"Variable":"packets_dropped","Now":0.0,"Min":0.0,"Max":0.0,"Avg":0.0}]