[{"Variable":"runtime","Now":108.33,"Min":84.33,"Max":108.33,"Avg":96.33},{"Variable":"ping","Now":0.0,"Min":0.0,"Max":0.0,"Avg":0.0},{"Variable":"adc_vb_f","Now":11.609,"Min":11.609,"Max":11.99,"Avg":11.83},{"Variable":"adc_va_f","Now":0.916,"Min":0.729,"Max":34.863,"Avg":11.97},{"Variable":"adc_vl_f","Now":11.581,"Min":11.581,"Max":12.061,"Avg":11.81},{"Variable":"adc_ic_f","Now":0.0,"Min":0.0,"Max":1.423,"Avg":0.16},{"Variable":"adc_il_f","Now":1.201,"Min":1.09,"Max":1.237,"Avg":1.17},{"Variable":"t_hs","Now":13.0,"Min":10.0,"Max":16.0,"Avg":12.27},{"Variable":"t_batt","Now":14.0,"Min":11.0,"Max":16.0,"Avg":12.77},{"Variable":"t_amb","Now":14.0,"Min":11.0,"Max":16.0,"Avg":12.77},{"Variable":"t_rts","Now":25.0,"Min":25.0,"Max":25.0,"Avg":25.0},{"Variable":"charge_state","Now":3.0,"Min":3.0,"Max":5.0,"Avg":3.83},{"Variable":"array_fault","Now":0.0,"Min":0.0,"Max":0.0,"Avg":0.0},{"Variable":"vb_f","Now":11.609,"Min":11.609,"Max":11.996,"Avg":11.83},{"Variable":"vb_ref","Now":0.0,"Min":0.0,"Max":14.728,"Avg":6.07},{"Variable":"ahc_r","Now":77.5,"Min":74.1,"Max":77.5,"Avg":76.07},{"Variable":"ahc_t","Now":77.5,"Min":74.1,"Max":77.5,"Avg":76.07},{"Variable":"kwhc","Now":1.0,"Min":1.0,"Max":1.0,"Avg":1.0},{"Variable":"load_state","Now":1.0,"Min":1.0,"Max":1.0,"Avg":1.0},{"Variable":"load_fault","Now":0.0,"Min":0.0,"Max":0.0,"Avg":0.0},{"Variable":"v_lvd","Now":11.484,"Min":11.484,"Max":11.499,"Avg":11.49},{"Variable":"ahl_r","Now":116.6,"Min":88.6,"Max":116.6,"Avg":102.53},{"Variable":"ahl_t","Now":116.6,"Min":88.6,"Max":116.6,"Avg":102.53},{"Variable":"hourmeter","Now":8360.0,"Min":8336.0,"Max":8360.0,"Avg":8347.98},{"Variable":"alarm","Now":1.0,"Min":1.0,"Max":1.0,"Avg":1.0},{"Variable":"dip_switch","Now":1101.0,"Min":1101.0,"Max":1101.0,"Avg":1101.0},{"Variable":"led_state","Now":10.0,"Min":8.0,"Max":10.0,"Avg":8.26},{"Variable":"power_out","Now":0.0,"Min":0.0,"Max":17.031,"Avg":1.85},{"Variable":"power_load","Now":13.909,"Min":12.79,"Max":14.762,"Avg":13.84},{"Variable":"sweep_vmp","Now":7.727,"Min":7.727,"Max":34.903,"Avg":15.77},{"Variable":"sweep_pmax","Now":4.213,"Min":3.744,"Max":17.56,"Avg":5.26},{"Variable":"sweep_voc","Now":10.306,"Min":10.306,"Max":40.463,"Avg":20.13},{"Variable":"vb_min_daily","Now":11.606,"Min":11.606,"Max":11.975,"Avg":11.79},{"Variable":"vb_max_daily","Now":11.761,"Min":11.761,"Max":12.146,"Avg":12.03},{"Variable":"ahc_daily","Now":0.0,"Min":0.0,"Max":3.4,"Avg":0.93},{"Variable":"ahl_daily","Now":8.7,"Min":0.0,"Max":27.9,"Avg":13.97},{"Variable":"array_fault_daily","Now":0.0,"Min":0.0,"Max":0.0,"Avg":0.0},{"Variable":"load_fault_daily","Now":0.0,"Min":0.0,"Max":0.0,"Avg":0.0},{"Variable":"alarm_daily","Now":1.0,"Min":1.0,"Max":1.0,"Avg":1.0},{"Variable":"vb_min","Now":9.439,"Min":9.439,"Max":9.439,"Avg":9.44},{"Variable":"vb_max","Now":19.47,"Min":19.47,"Max":19.47,"Avg":19.47},{"Variable":"sensor_uptime","Now":107.743,"Min":83.746,"Max":107.743,"Avg":95.74},{"Variable":"crc_errors","Now":0.0,"Min":0.0,"Max":0.0,"Avg":0.0},{"Variable":"crc_errors_delta","Now":0.0,"Min":0.0,"Max":0.0,"Avg":0.0},{"Variable":"crc_errors_hourly","Now":0.0,"Min":0.0,"Max":0.0,"Avg":0.0},{"Variable":"crc_errors_daily","Now":0.0,"Min":0.0,"Max":0.0,"Avg":0.0},{"Variable":"valid_packets","Now":549.0,"Min":498.0,"Max":549.0,"Avg":529.41},{"Variable":"trigger_delta","Now":0.0,"Min":0.0,"Max":1.0,"Avg":0.04},{"Variable":"trigger_rate_1min","Now":0.0,"Min":0.0,"Max":1.0,"Avg":0.04},{"Variable":"trigger_rate_5min","Now":0.0,"Min":0.0,"Max":0.6,"Avg":0.04},{"Variable":"trigger_rate_1hr","Now":0.0,"Min":0.0,"Max":0.15,"Avg":0.04},{"Variable":"bytes_read","Now":63.73,"Min":51.09,"Max":63.73,"Avg":57.54},{"Variable":"bytes_written","Now":12.08,"Min":10.96,"Max":12.08,"Avg":11.65},{"Variable":"bytes_remaining","Now":482.62,"Min":482.62,"Max":483.74,"Avg":483.05},{"Variable":"triggers_remaining","Now":21937.0,"Min":21937.0,"Max":21988.0,"Avg":21956.59},{"Variable":"packets_sent","Now":5.0,"Min":5.0,"Max":5.0,"Avg":5.0},{"Variable":"packets_dropped","Now":0.0,"Min":0.0,"Max":0.0,"Avg":0.0}]