[{"Variable":"runtime","Now":262.17,"Min":238.17,"Max":262.17,"Avg":250.17},{"Variable":"ping","Now":0.0,"Min":0.0,"Max":0.0,"Avg":0.0},{"Variable":"adc_vb_f","Now":12.329,"Min":12.073,"Max":14.24,"Avg":12.55},{"Variable":"adc_va_f","Now":32.077,"Min":0.711,"Max":41.65,"Avg":13.56},{"Variable":"adc_vl_f","Now":12.421,"Min":12.088,"Max":14.102,"Avg":12.54},{"Variable":"adc_ic_f","Now":1.606,"Min":0.0,"Max":9.252,"Avg":0.95},{"Variable":"adc_il_f","Now":1.16,"Min":0.582,"Max":1.71,"Avg":1.09},{"Variable":"t_hs","Now":27.0,"Min":20.0,"Max":35.0,"Avg":23.01},{"Variable":"t_batt","Now":26.0,"Min":20.0,"Max":32.0,"Avg":22.96},{"Variable":"t_amb","Now":26.0,"Min":20.0,"Max":32.0,"Avg":22.96},{"Variable":"t_rts","Now":25.0,"Min":25.0,"Max":25.0,"Avg":25.0},{"Variable":"charge_state","Now":5.0,"Min":3.0,"Max":6.0,"Avg":3.87},{"Variable":"array_fault","Now":0.0,"Min":0.0,"Max":0.0,"Avg":0.0},{"Variable":"vb_f","Now":12.326,"Min":12.097,"Max":14.212,"Avg":12.56},{"Variable":"vb_ref","Now":14.27,"Min":0.0,"Max":14.423,"Avg":5.97},{"Variable":"ahc_r","Now":289.8,"Min":267.2,"Max":289.8,"Avg":284.87},{"Variable":"ahc_t","Now":289.8,"Min":267.2,"Max":289.8,"Avg":284.87},{"Variable":"kwhc","Now":3.9,"Min":3.6,"Max":3.9,"Avg":3.8},{"Variable":"load_state","Now":1.0,"Min":1.0,"Max":1.0,"Avg":1.0},{"Variable":"load_fault","Now":0.0,"Min":0.0,"Max":0.0,"Avg":0.0},{"Variable":"v_lvd","Now":11.499,"Min":11.484,"Max":11.499,"Avg":11.49},{"Variable":"ahl_r","Now":267.4,"Min":241.3,"Max":267.4,"Avg":253.84},{"Variable":"ahl_t","Now":267.4,"Min":241.3,"Max":267.4,"Avg":253.84},{"Variable":"hourmeter","Now":8514.0,"Min":8490.0,"Max":8514.0,"Avg":8501.84},{"Variable":"alarm","Now":1.0,"Min":1.0,"Max":1.0,"Avg":1.0},{"Variable":"dip_switch","Now":1101.0,"Min":1101.0,"Max":1101.0,"Avg":1101.0},{"Variable":"led_state","Now":8.0,"Min":5.0,"Max":8.0,"Avg":6.16},{"Variable":"power_out","Now":19.764,"Min":0.0,"Max":130.708,"Avg":12.75},{"Variable":"power_load","Now":14.408,"Min":8.207,"Max":20.67,"Avg":13.63},{"Variable":"sweep_vmp","Now":32.123,"Min":8.044,"Max":34.949,"Avg":17.28},{"Variable":"sweep_pmax","Now":20.474,"Min":4.031,"Max":118.69,"Avg":16.06},{"Variable":"sweep_voc","Now":38.873,"Min":10.727,"Max":42.139,"Avg":21.7},{"Variable":"vb_min_daily","Now":12.07,"Min":12.027,"Max":12.521,"Avg":12.2},{"Variable":"vb_max_daily","Now":12.68,"Min":12.527,"Max":14.31,"Avg":13.04},{"Variable":"ahc_daily","Now":3.5,"Min":0.0,"Max":34.3,"Avg":8.42},{"Variable":"ahl_daily","Now":19.5,"Min":0.0,"Max":25.5,"Avg":13.27},{"Variable":"array_fault_daily","Now":0.0,"Min":0.0,"Max":0.0,"Avg":0.0},{"Variable":"load_fault_daily","Now":0.0,"Min":0.0,"Max":0.0,"Avg":0.0},{"Variable":"alarm_daily","Now":1.0,"Min":1.0,"Max":1.0,"Avg":1.0},{"Variable":"vb_min","Now":9.439,"Min":9.439,"Max":9.439,"Avg":9.44},{"Variable":"vb_max","Now":19.47,"Min":19.47,"Max":19.47,"Avg":19.47},{"Variable":"sensor_uptime","Now":121.913,"Min":97.916,"Max":121.913,"Avg":109.91},{"Variable":"crc_errors","Now":0.0,"Min":0.0,"Max":0.0,"Avg":0.0},{"Variable":"crc_errors_delta","Now":0.0,"Min":0.0,"Max":0.0,"Avg":0.0},{"Variable":"crc_errors_hourly","Now":0.0,"Min":0.0,"Max":0.0,"Avg":0.0},{"Variable":"crc_errors_daily","Now":0.0,"Min":0.0,"Max":0.0,"Avg":0.0},{"Variable":"valid_packets","Now":304.0,"Min":216.0,"Max":304.0,"Avg":255.63},{"Variable":"trigger_delta","Now":0.0,"Min":0.0,"Max":2.0,"Avg":0.06},{"Variable":"trigger_rate_1min","Now":0.0,"Min":0.0,"Max":2.0,"Avg":0.06},{"Variable":"trigger_rate_5min","Now":0.0,"Min":0.0,"Max":0.8,"Avg":0.06},{"Variable":"trigger_rate_1hr","Now":0.05,"Min":0.0,"Max":0.183,"Avg":0.06},{"Variable":"bytes_read","Now":65.17,"Min":51.73,"Max":65.17,"Avg":58.36},{"Variable":"bytes_written","Now":6.69,"Min":4.75,"Max":6.69,"Avg":5.62},{"Variable":"bytes_remaining","Now":471.73,"Min":471.73,"Max":473.67,"Avg":472.8},{"Variable":"triggers_remaining","Now":21442.0,"Min":21442.0,"Max":21530.0,"Avg":21490.37},{"Variable":"packets_sent","Now":0.0,"Min":0.0,"Max":0.0,"Avg":0.0},{"Variable":"packets_dropped","Now":0.0,"Min":0.0,"Max":0.0,"Avg":0.0}]