[{"Variable":"runtime","Now":338.17,"Min":314.18,"Max":338.17,"Avg":326.18},{"Variable":"ping","Now":0.0,"Min":0.0,"Max":0.0,"Avg":0.0},{"Variable":"adc_vb_f","Now":14.243,"Min":12.106,"Max":14.572,"Avg":12.95},{"Variable":"adc_va_f","Now":37.46,"Min":0.623,"Max":42.77,"Avg":16.7},{"Variable":"adc_vl_f","Now":14.221,"Min":12.115,"Max":14.453,"Avg":12.9},{"Variable":"adc_ic_f","Now":2.563,"Min":0.0,"Max":9.777,"Avg":1.3},{"Variable":"adc_il_f","Now":0.954,"Min":0.647,"Max":1.169,"Avg":1.02},{"Variable":"t_hs","Now":28.0,"Min":3.0,"Max":36.0,"Avg":14.34},{"Variable":"t_batt","Now":26.0,"Min":3.0,"Max":34.0,"Avg":14.05},{"Variable":"t_amb","Now":26.0,"Min":3.0,"Max":34.0,"Avg":14.05},{"Variable":"t_rts","Now":25.0,"Min":25.0,"Max":25.0,"Avg":25.0},{"Variable":"charge_state","Now":6.0,"Min":3.0,"Max":6.0,"Avg":4.18},{"Variable":"array_fault","Now":0.0,"Min":0.0,"Max":0.0,"Avg":0.0},{"Variable":"vb_f","Now":14.27,"Min":12.115,"Max":14.523,"Avg":12.95},{"Variable":"vb_ref","Now":14.27,"Min":0.0,"Max":14.972,"Avg":6.38},{"Variable":"ahc_r","Now":407.9,"Min":376.6,"Max":407.9,"Avg":385.24},{"Variable":"ahc_t","Now":407.9,"Min":376.6,"Max":407.9,"Avg":385.24},{"Variable":"kwhc","Now":5.5,"Min":5.1,"Max":5.5,"Avg":5.24},{"Variable":"load_state","Now":1.0,"Min":1.0,"Max":1.0,"Avg":1.0},{"Variable":"load_fault","Now":0.0,"Min":0.0,"Max":0.0,"Avg":0.0},{"Variable":"v_lvd","Now":11.499,"Min":11.484,"Max":11.499,"Avg":11.49},{"Variable":"ahl_r","Now":345.4,"Min":321.2,"Max":345.4,"Avg":333.9},{"Variable":"ahl_t","Now":345.4,"Min":321.2,"Max":345.4,"Avg":333.9},{"Variable":"hourmeter","Now":8590.0,"Min":8566.0,"Max":8590.0,"Avg":8577.85},{"Variable":"alarm","Now":1.0,"Min":1.0,"Max":1.0,"Avg":1.0},{"Variable":"dip_switch","Now":1101.0,"Min":1101.0,"Max":1101.0,"Avg":1101.0},{"Variable":"led_state","Now":5.0,"Min":2.0,"Max":6.0,"Avg":5.7},{"Variable":"power_out","Now":42.17,"Min":0.0,"Max":143.014,"Avg":18.24},{"Variable":"power_load","Now":13.567,"Min":9.026,"Max":15.323,"Avg":13.0},{"Variable":"sweep_vmp","Now":35.257,"Min":8.084,"Max":39.813,"Avg":19.36},{"Variable":"sweep_pmax","Now":40.525,"Min":4.56,"Max":126.013,"Avg":36.57},{"Variable":"sweep_voc","Now":41.052,"Min":10.782,"Max":44.421,"Avg":24.05},{"Variable":"vb_min_daily","Now":12.106,"Min":12.106,"Max":12.589,"Avg":12.24},{"Variable":"vb_max_daily","Now":14.615,"Min":12.592,"Max":14.615,"Avg":13.36},{"Variable":"ahc_daily","Now":26.7,"Min":0.0,"Max":32.3,"Avg":8.28},{"Variable":"ahl_daily","Now":21.0,"Min":0.0,"Max":24.5,"Avg":12.71},{"Variable":"array_fault_daily","Now":0.0,"Min":0.0,"Max":0.0,"Avg":0.0},{"Variable":"load_fault_daily","Now":0.0,"Min":0.0,"Max":0.0,"Avg":0.0},{"Variable":"alarm_daily","Now":1.0,"Min":1.0,"Max":1.0,"Avg":1.0},{"Variable":"vb_min","Now":9.439,"Min":9.439,"Max":9.439,"Avg":9.44},{"Variable":"vb_max","Now":19.47,"Min":19.47,"Max":19.47,"Avg":19.47},{"Variable":"sensor_uptime","Now":197.901,"Min":173.921,"Max":197.901,"Avg":185.91},{"Variable":"crc_errors","Now":0.0,"Min":0.0,"Max":0.0,"Avg":0.0},{"Variable":"crc_errors_delta","Now":0.0,"Min":0.0,"Max":0.0,"Avg":0.0},{"Variable":"crc_errors_hourly","Now":0.0,"Min":0.0,"Max":0.0,"Avg":0.0},{"Variable":"crc_errors_daily","Now":0.0,"Min":0.0,"Max":0.0,"Avg":0.0},{"Variable":"valid_packets","Now":1395.0,"Min":1378.0,"Max":1395.0,"Avg":1386.89},{"Variable":"trigger_delta","Now":0.0,"Min":0.0,"Max":1.0,"Avg":0.01},{"Variable":"trigger_rate_1min","Now":0.0,"Min":0.0,"Max":1.0,"Avg":0.01},{"Variable":"trigger_rate_5min","Now":0.0,"Min":0.0,"Max":0.4,"Avg":0.01},{"Variable":"trigger_rate_1hr","Now":0.0,"Min":0.0,"Max":0.067,"Avg":0.01},{"Variable":"bytes_read","Now":125.51,"Min":113.63,"Max":125.51,"Avg":119.58},{"Variable":"bytes_written","Now":30.69,"Min":30.32,"Max":30.69,"Avg":30.51},{"Variable":"bytes_remaining","Now":447.73,"Min":447.73,"Max":448.1,"Avg":447.91},{"Variable":"triggers_remaining","Now":20351.0,"Min":20351.0,"Max":20368.0,"Avg":20359.11},{"Variable":"packets_sent","Now":0.0,"Min":0.0,"Max":0.0,"Avg":0.0},{"Variable":"packets_dropped","Now":0.0,"Min":0.0,"Max":0.0,"Avg":0.0}]