[{"Variable":"runtime","Now":237.73,"Min":213.73,"Max":237.73,"Avg":225.73},{"Variable":"adc_vb_f","Now":12.82,"Min":12.073,"Max":13.205,"Avg":12.5},{"Variable":"adc_va_f","Now":16.263,"Min":0.0,"Max":18.073,"Avg":9.75},{"Variable":"adc_vl_f","Now":12.738,"Min":12.048,"Max":13.156,"Avg":12.46},{"Variable":"adc_ic_f","Now":5.641,"Min":0.0,"Max":8.75,"Avg":2.68},{"Variable":"adc_il_f","Now":1.73,"Min":1.664,"Max":2.367,"Avg":1.85},{"Variable":"t_hs","Now":34.0,"Min":21.0,"Max":53.0,"Avg":34.6},{"Variable":"t_batt","Now":35.0,"Min":22.0,"Max":52.0,"Avg":34.67},{"Variable":"t_amb","Now":35.0,"Min":22.0,"Max":52.0,"Avg":34.67},{"Variable":"t_rts","Now":25.0,"Min":25.0,"Max":25.0,"Avg":25.0},{"Variable":"charge_state","Now":5.0,"Min":1.0,"Max":6.0,"Avg":4.23},{"Variable":"array_fault","Now":0.0,"Min":0.0,"Max":0.0,"Avg":0.0},{"Variable":"vb_f","Now":12.82,"Min":12.097,"Max":13.205,"Avg":12.5},{"Variable":"vb_ref","Now":13.721,"Min":0.0,"Max":14.104,"Avg":8.32},{"Variable":"ahc_r","Now":1234.3,"Min":1170.7,"Max":1234.3,"Avg":1220.7},{"Variable":"ahc_t","Now":1234.3,"Min":1170.7,"Max":1234.3,"Avg":1220.7},{"Variable":"kwhc","Now":15.9,"Min":15.0,"Max":15.9,"Avg":15.68},{"Variable":"load_state","Now":1.0,"Min":1.0,"Max":1.0,"Avg":1.0},{"Variable":"load_fault","Now":0.0,"Min":0.0,"Max":0.0,"Avg":0.0},{"Variable":"v_lvd","Now":11.499,"Min":11.469,"Max":11.499,"Avg":11.48},{"Variable":"ahl_r","Now":1204.8,"Min":1160.4,"Max":1204.8,"Avg":1182.13},{"Variable":"ahl_t","Now":1204.8,"Min":1160.4,"Max":1204.8,"Avg":1182.13},{"Variable":"hourmeter","Now":4040.0,"Min":4016.0,"Max":4040.0,"Avg":4027.66},{"Variable":"alarm","Now":1.0,"Min":1.0,"Max":1.0,"Avg":1.0},{"Variable":"dip_switch","Now":13.0,"Min":13.0,"Max":13.0,"Avg":13.0},{"Variable":"led_state","Now":8.0,"Min":2.0,"Max":8.0,"Avg":6.54},{"Variable":"power_out","Now":72.277,"Min":0.0,"Max":114.81,"Avg":34.74},{"Variable":"power_load","Now":22.037,"Min":21.253,"Max":30.96,"Avg":23.03},{"Variable":"power_net","Now":47.44,"Min":-28.633,"Max":89.877,"Avg":8.92},{"Variable":"sweep_vmp","Now":16.275,"Min":8.292,"Max":18.106,"Avg":12.64},{"Variable":"sweep_pmax","Now":72.518,"Min":3.125,"Max":114.462,"Avg":36.37},{"Variable":"sweep_voc","Now":20.135,"Min":11.057,"Max":20.764,"Avg":16.07},{"Variable":"vb_min_daily","Now":12.064,"Min":11.948,"Max":12.299,"Avg":12.07},{"Variable":"vb_max_daily","Now":12.83,"Min":12.302,"Max":13.205,"Avg":12.66},{"Variable":"ahc_daily","Now":4.1,"Min":0.0,"Max":63.1,"Avg":18.14},{"Variable":"ahl_daily","Now":25.8,"Min":0.0,"Max":44.4,"Avg":22.62},{"Variable":"ahnet_daily","Now":-21.7,"Min":-23.6,"Max":22.5,"Avg":-4.48},{"Variable":"array_fault_daily","Now":0.0,"Min":0.0,"Max":0.0,"Avg":0.0},{"Variable":"load_fault_daily","Now":0.0,"Min":0.0,"Max":0.0,"Avg":0.0},{"Variable":"alarm_daily","Now":1.0,"Min":1.0,"Max":1.0,"Avg":1.0},{"Variable":"vb_min","Now":10.779,"Min":10.779,"Max":10.779,"Avg":10.78},{"Variable":"vb_max","Now":20.898,"Min":20.898,"Max":20.898,"Avg":20.9},{"Variable":"sensor_uptime","Now":241.868,"Min":217.871,"Max":241.868,"Avg":229.87},{"Variable":"ping","Now":0.0,"Min":0.0,"Max":0.0,"Avg":0.0},{"Variable":"crc_errors","Now":2.0,"Min":2.0,"Max":2.0,"Avg":2.0},{"Variable":"crc_errors_delta","Now":0.0,"Min":0.0,"Max":0.0,"Avg":0.0},{"Variable":"crc_errors_hourly","Now":0.0,"Min":0.0,"Max":0.0,"Avg":0.0},{"Variable":"crc_errors_daily","Now":0.0,"Min":0.0,"Max":0.0,"Avg":0.0},{"Variable":"valid_packets","Now":1875.0,"Min":1868.0,"Max":1875.0,"Avg":1871.38},{"Variable":"trigger_delta","Now":0.0,"Min":0.0,"Max":1.0,"Avg":0.0},{"Variable":"trigger_rate_1min","Now":0.0,"Min":0.0,"Max":6.0,"Avg":0.0},{"Variable":"trigger_rate_5min","Now":0.0,"Min":0.0,"Max":1.2,"Avg":0.0},{"Variable":"trigger_rate_1hr","Now":0.0,"Min":0.0,"Max":0.2,"Avg":0.0},{"Variable":"bytes_read","Now":157.18,"Min":145.51,"Max":157.18,"Avg":151.34},{"Variable":"bytes_written","Now":41.25,"Min":41.1,"Max":41.25,"Avg":41.17},{"Variable":"bytes_remaining","Now":278.87,"Min":278.87,"Max":279.03,"Avg":278.95},{"Variable":"triggers_remaining","Now":12676.0,"Min":12676.0,"Max":12683.0,"Avg":12679.62},{"Variable":"packets_sent","Now":0.0,"Min":0.0,"Max":0.0,"Avg":0.0},{"Variable":"packets_dropped","Now":0.0,"Min":0.0,"Max":0.0,"Avg":0.0}]