[{"Variable":"runtime","Now":35.83,"Min":11.83,"Max":35.83,"Avg":23.83},{"Variable":"ping","Now":0.0,"Min":0.0,"Max":0.0,"Avg":0.0},{"Variable":"adc_vb_f","Now":12.357,"Min":12.07,"Max":14.828,"Avg":12.99},{"Variable":"adc_va_f","Now":0.601,"Min":0.546,"Max":41.821,"Avg":16.54},{"Variable":"adc_vl_f","Now":12.344,"Min":12.115,"Max":14.639,"Avg":12.94},{"Variable":"adc_ic_f","Now":0.002,"Min":0.0,"Max":7.474,"Avg":1.21},{"Variable":"adc_il_f","Now":1.097,"Min":0.621,"Max":1.22,"Avg":1.03},{"Variable":"t_hs","Now":3.0,"Min":0.0,"Max":31.0,"Avg":11.11},{"Variable":"t_batt","Now":3.0,"Min":0.0,"Max":28.0,"Avg":10.65},{"Variable":"t_amb","Now":3.0,"Min":0.0,"Max":28.0,"Avg":10.65},{"Variable":"t_rts","Now":25.0,"Min":25.0,"Max":25.0,"Avg":25.0},{"Variable":"charge_state","Now":3.0,"Min":3.0,"Max":6.0,"Avg":4.18},{"Variable":"array_fault","Now":0.0,"Min":0.0,"Max":0.0,"Avg":0.0},{"Variable":"vb_f","Now":12.36,"Min":12.088,"Max":14.819,"Avg":13.0},{"Variable":"vb_ref","Now":0.0,"Min":0.0,"Max":14.999,"Avg":6.39},{"Variable":"ahc_r","Now":34.3,"Min":5.3,"Max":34.3,"Avg":20.81},{"Variable":"ahc_t","Now":34.3,"Min":5.3,"Max":34.3,"Avg":20.81},{"Variable":"kwhc","Now":0.4,"Min":0.0,"Max":0.4,"Avg":0.22},{"Variable":"load_state","Now":1.0,"Min":1.0,"Max":1.0,"Avg":1.0},{"Variable":"load_fault","Now":0.0,"Min":0.0,"Max":0.0,"Avg":0.0},{"Variable":"v_lvd","Now":11.484,"Min":11.484,"Max":11.499,"Avg":11.49},{"Variable":"ahl_r","Now":36.6,"Min":12.0,"Max":36.6,"Avg":24.34},{"Variable":"ahl_t","Now":36.6,"Min":12.0,"Max":36.6,"Avg":24.34},{"Variable":"hourmeter","Now":8287.0,"Min":8263.0,"Max":8287.0,"Avg":8275.47},{"Variable":"alarm","Now":1.0,"Min":1.0,"Max":1.0,"Avg":1.0},{"Variable":"dip_switch","Now":1101.0,"Min":1101.0,"Max":1101.0,"Avg":1101.0},{"Variable":"led_state","Now":6.0,"Min":5.0,"Max":8.0,"Avg":5.83},{"Variable":"power_out","Now":0.0,"Min":0.0,"Max":110.839,"Avg":17.06},{"Variable":"power_load","Now":13.541,"Min":8.725,"Max":15.063,"Avg":13.2},{"Variable":"sweep_vmp","Now":7.651,"Min":7.651,"Max":39.355,"Avg":19.9},{"Variable":"sweep_pmax","Now":8.138,"Min":4.394,"Max":117.105,"Avg":40.25},{"Variable":"sweep_voc","Now":10.202,"Min":10.202,"Max":44.092,"Avg":24.34},{"Variable":"vb_min_daily","Now":12.344,"Min":12.07,"Max":12.604,"Avg":12.21},{"Variable":"vb_max_daily","Now":12.604,"Min":12.604,"Max":14.905,"Avg":14.24},{"Variable":"ahc_daily","Now":0.0,"Min":0.0,"Max":34.3,"Avg":11.29},{"Variable":"ahl_daily","Now":7.3,"Min":0.0,"Max":29.3,"Avg":16.21},{"Variable":"array_fault_daily","Now":0.0,"Min":0.0,"Max":0.0,"Avg":0.0},{"Variable":"load_fault_daily","Now":0.0,"Min":0.0,"Max":0.0,"Avg":0.0},{"Variable":"alarm_daily","Now":1.0,"Min":1.0,"Max":1e+18,"Avg":7.22e+17},{"Variable":"vb_min","Now":9.439,"Min":9.439,"Max":9.439,"Avg":9.44},{"Variable":"vb_max","Now":19.47,"Min":19.47,"Max":19.47,"Avg":19.47},{"Variable":"sensor_uptime","Now":35.253,"Min":11.256,"Max":35.253,"Avg":23.25},{"Variable":"crc_errors","Now":0.0,"Min":0.0,"Max":0.0,"Avg":0.0},{"Variable":"crc_errors_delta","Now":0.0,"Min":0.0,"Max":0.0,"Avg":0.0},{"Variable":"crc_errors_hourly","Now":0.0,"Min":0.0,"Max":0.0,"Avg":0.0},{"Variable":"crc_errors_daily","Now":0.0,"Min":0.0,"Max":0.0,"Avg":0.0},{"Variable":"valid_packets","Now":240.0,"Min":136.0,"Max":240.0,"Avg":215.14},{"Variable":"trigger_delta","Now":0.0,"Min":0.0,"Max":2.0,"Avg":0.07},{"Variable":"trigger_rate_1min","Now":0.0,"Min":0.0,"Max":2.0,"Avg":0.07},{"Variable":"trigger_rate_5min","Now":0.0,"Min":0.0,"Max":1.4,"Avg":0.07},{"Variable":"trigger_rate_1hr","Now":0.017,"Min":0.0,"Max":0.533,"Avg":0.07},{"Variable":"bytes_read","Now":22.17,"Min":8.38,"Max":22.17,"Avg":15.87},{"Variable":"bytes_written","Now":5.28,"Min":2.99,"Max":5.28,"Avg":4.73},{"Variable":"bytes_remaining","Now":489.42,"Min":489.42,"Max":491.71,"Avg":489.97},{"Variable":"triggers_remaining","Now":22246.0,"Min":22246.0,"Max":22350.0,"Avg":22270.86},{"Variable":"packets_sent","Now":5.0,"Min":5.0,"Max":5.0,"Avg":5.0},{"Variable":"packets_dropped","Now":0.0,"Min":0.0,"Max":0.0,"Avg":0.0}]