[{"Variable":"runtime","Now":419.52,"Min":395.52,"Max":419.52,"Avg":407.52},{"Variable":"adc_vb_f","Now":11.951,"Min":11.948,"Max":13.245,"Avg":12.27},{"Variable":"adc_va_f","Now":0.0,"Min":0.0,"Max":18.167,"Avg":9.01},{"Variable":"adc_vl_f","Now":11.899,"Min":11.899,"Max":13.232,"Avg":12.23},{"Variable":"adc_ic_f","Now":0.005,"Min":0.0,"Max":9.62,"Avg":1.59},{"Variable":"adc_il_f","Now":2.0,"Min":1.71,"Max":2.447,"Avg":1.95},{"Variable":"t_hs","Now":28.0,"Min":28.0,"Max":57.0,"Avg":36.2},{"Variable":"t_batt","Now":29.0,"Min":29.0,"Max":55.0,"Avg":36.67},{"Variable":"t_amb","Now":29.0,"Min":29.0,"Max":55.0,"Avg":36.67},{"Variable":"t_rts","Now":25.0,"Min":25.0,"Max":25.0,"Avg":25.0},{"Variable":"charge_state","Now":3.0,"Min":3.0,"Max":5.0,"Avg":4.18},{"Variable":"array_fault","Now":0.0,"Min":0.0,"Max":0.0,"Avg":0.0},{"Variable":"vb_f","Now":11.948,"Min":11.948,"Max":13.226,"Avg":12.27},{"Variable":"vb_ref","Now":0.0,"Min":0.0,"Max":13.706,"Avg":7.88},{"Variable":"ahc_r","Now":1061.5,"Min":1024.0,"Max":1061.5,"Avg":1049.14},{"Variable":"ahc_t","Now":1061.5,"Min":1024.0,"Max":1061.5,"Avg":1049.14},{"Variable":"kwhc","Now":13.8,"Min":13.3,"Max":13.8,"Avg":13.64},{"Variable":"load_state","Now":1.0,"Min":1.0,"Max":1.0,"Avg":1.0},{"Variable":"load_fault","Now":0.0,"Min":0.0,"Max":0.0,"Avg":0.0},{"Variable":"v_lvd","Now":11.472,"Min":11.469,"Max":11.499,"Avg":11.48},{"Variable":"ahl_r","Now":944.4,"Min":897.6,"Max":944.4,"Avg":920.75},{"Variable":"ahl_t","Now":944.4,"Min":897.6,"Max":944.4,"Avg":920.75},{"Variable":"hourmeter","Now":5027.0,"Min":5003.0,"Max":5027.0,"Avg":5015.41},{"Variable":"alarm","Now":1.0,"Min":1.0,"Max":1.0,"Avg":1.0},{"Variable":"dip_switch","Now":13.0,"Min":13.0,"Max":13.0,"Avg":13.0},{"Variable":"led_state","Now":8.0,"Min":6.0,"Max":8.0,"Avg":7.2},{"Variable":"power_out","Now":0.015,"Min":0.0,"Max":126.451,"Avg":20.33},{"Variable":"power_load","Now":23.798,"Min":22.126,"Max":29.721,"Avg":23.87},{"Variable":"power_net","Now":-26.583,"Min":-29.158,"Max":100.549,"Avg":-6.34},{"Variable":"sweep_vmp","Now":8.292,"Min":8.292,"Max":18.21,"Avg":12.15},{"Variable":"sweep_pmax","Now":3.156,"Min":3.156,"Max":128.715,"Avg":21.81},{"Variable":"sweep_voc","Now":11.057,"Min":11.057,"Max":20.779,"Avg":15.52},{"Variable":"vb_min_daily","Now":11.938,"Min":11.938,"Max":12.112,"Avg":11.98},{"Variable":"vb_max_daily","Now":12.14,"Min":12.14,"Max":13.245,"Avg":12.61},{"Variable":"ahc_daily","Now":0.0,"Min":0.0,"Max":37.5,"Avg":11.76},{"Variable":"ahl_daily","Now":17.1,"Min":0.0,"Max":46.6,"Avg":23.43},{"Variable":"ahnet_daily","Now":-17.1,"Min":-25.3,"Max":0.0,"Avg":-11.66},{"Variable":"array_fault_daily","Now":0.0,"Min":0.0,"Max":0.0,"Avg":0.0},{"Variable":"load_fault_daily","Now":0.0,"Min":0.0,"Max":0.0,"Avg":0.0},{"Variable":"alarm_daily","Now":1.0,"Min":1.0,"Max":1.0,"Avg":1.0},{"Variable":"vb_min","Now":10.779,"Min":10.779,"Max":10.779,"Avg":10.78},{"Variable":"vb_max","Now":20.898,"Min":20.898,"Max":20.898,"Avg":20.9},{"Variable":"sensor_uptime","Now":326.149,"Min":302.157,"Max":326.149,"Avg":314.15},{"Variable":"ping","Now":0.0,"Min":0.0,"Max":0.0,"Avg":0.0},{"Variable":"crc_errors","Now":0.0,"Min":0.0,"Max":0.0,"Avg":0.0},{"Variable":"crc_errors_delta","Now":0.0,"Min":0.0,"Max":0.0,"Avg":0.0},{"Variable":"crc_errors_hourly","Now":0.0,"Min":0.0,"Max":0.0,"Avg":0.0},{"Variable":"crc_errors_daily","Now":0.0,"Min":0.0,"Max":0.0,"Avg":0.0},{"Variable":"valid_packets","Now":4437.0,"Min":3133.0,"Max":4437.0,"Avg":3686.66},{"Variable":"trigger_delta","Now":0.0,"Min":0.0,"Max":17.0,"Avg":0.9},{"Variable":"trigger_rate_1min","Now":0.0,"Min":0.0,"Max":17.0,"Avg":0.9},{"Variable":"trigger_rate_5min","Now":0.0,"Min":0.0,"Max":14.8,"Avg":0.9},{"Variable":"trigger_rate_1hr","Now":0.0,"Min":0.0,"Max":9.633,"Avg":0.9},{"Variable":"bytes_read","Now":253.6,"Min":213.57,"Max":253.6,"Avg":231.44},{"Variable":"bytes_written","Now":97.61,"Min":68.93,"Max":97.61,"Avg":81.11},{"Variable":"bytes_remaining","Now":41.98,"Min":41.98,"Max":70.66,"Avg":58.48},{"Variable":"triggers_remaining","Now":1908.0,"Min":1908.0,"Max":3212.0,"Avg":2658.34},{"Variable":"packets_sent","Now":0.0,"Min":0.0,"Max":0.0,"Avg":0.0},{"Variable":"packets_dropped","Now":0.0,"Min":0.0,"Max":0.0,"Avg":0.0}]