[{"Variable":"runtime","Now":53.17,"Min":29.17,"Max":53.17,"Avg":41.17},{"Variable":"ping","Now":1.0,"Min":1.0,"Max":2.0,"Avg":1.0},{"Variable":"adc_vb_f","Now":13.486,"Min":12.567,"Max":14.755,"Avg":13.25},{"Variable":"adc_va_f","Now":30.27,"Min":0.546,"Max":41.843,"Avg":16.56},{"Variable":"adc_vl_f","Now":0.0,"Min":0.0,"Max":0.0,"Avg":0.0},{"Variable":"adc_ic_f","Now":0.314,"Min":0.0,"Max":0.611,"Avg":0.2},{"Variable":"adc_il_f","Now":0.0,"Min":0.0,"Max":0.0,"Avg":0.0},{"Variable":"t_hs","Now":10.0,"Min":9.0,"Max":16.0,"Avg":10.51},{"Variable":"t_batt","Now":11.0,"Min":10.0,"Max":16.0,"Avg":10.65},{"Variable":"t_amb","Now":11.0,"Min":10.0,"Max":16.0,"Avg":10.65},{"Variable":"t_rts","Now":25.0,"Min":25.0,"Max":25.0,"Avg":25.0},{"Variable":"charge_state","Now":7.0,"Min":1.0,"Max":7.0,"Avg":4.57},{"Variable":"array_fault","Now":0.0,"Min":0.0,"Max":0.0,"Avg":0.0},{"Variable":"vb_f","Now":13.51,"Min":12.573,"Max":14.755,"Avg":13.25},{"Variable":"vb_ref","Now":14.127,"Min":0.0,"Max":14.758,"Avg":7.27},{"Variable":"ahc_r","Now":783.1,"Min":778.5,"Max":783.1,"Avg":779.63},{"Variable":"ahc_t","Now":783.1,"Min":778.5,"Max":783.1,"Avg":779.63},{"Variable":"kwhc","Now":10.7,"Min":10.7,"Max":10.7,"Avg":10.7},{"Variable":"load_state","Now":5.0,"Min":5.0,"Max":5.0,"Avg":5.0},{"Variable":"load_fault","Now":0.0,"Min":0.0,"Max":0.0,"Avg":0.0},{"Variable":"v_lvd","Now":11.499,"Min":11.499,"Max":11.499,"Avg":11.5},{"Variable":"ahl_r","Now":658.0,"Min":658.0,"Max":658.0,"Avg":658.0},{"Variable":"ahl_t","Now":658.0,"Min":658.0,"Max":658.0,"Avg":658.0},{"Variable":"hourmeter","Now":9119.0,"Min":9095.0,"Max":9119.0,"Avg":9107.39},{"Variable":"alarm","Now":1.0,"Min":1.0,"Max":1.0,"Avg":1.0},{"Variable":"dip_switch","Now":1101.0,"Min":1101.0,"Max":1101.0,"Avg":1101.0},{"Variable":"led_state","Now":11.0,"Min":4.0,"Max":11.0,"Avg":10.54},{"Variable":"power_out","Now":4.258,"Min":0.0,"Max":8.953,"Avg":2.8},{"Variable":"power_load","Now":0.0,"Min":0.0,"Max":0.0,"Avg":0.0},{"Variable":"sweep_vmp","Now":30.292,"Min":0.415,"Max":37.686,"Avg":14.54},{"Variable":"sweep_pmax","Now":6.311,"Min":4.016,"Max":39.815,"Avg":6.93},{"Variable":"sweep_voc","Now":38.217,"Min":0.555,"Max":43.335,"Avg":17.99},{"Variable":"vb_min_daily","Now":12.311,"Min":10.025,"Max":12.717,"Avg":12.18},{"Variable":"vb_max_daily","Now":14.908,"Min":12.72,"Max":15.051,"Avg":13.75},{"Variable":"ahc_daily","Now":4.2,"Min":0.0,"Max":12.4,"Avg":2.35},{"Variable":"ahl_daily","Now":0.0,"Min":0.0,"Max":7.5,"Avg":0.98},{"Variable":"array_fault_daily","Now":0.0,"Min":0.0,"Max":0.0,"Avg":0.0},{"Variable":"load_fault_daily","Now":0.0,"Min":0.0,"Max":0.0,"Avg":0.0},{"Variable":"alarm_daily","Now":1.0,"Min":1.0,"Max":1e+19,"Avg":1.3e+18},{"Variable":"vb_min","Now":9.439,"Min":9.439,"Max":9.439,"Avg":9.44},{"Variable":"vb_max","Now":19.47,"Min":19.47,"Max":19.47,"Avg":19.47},{"Variable":"sensor_uptime","Now":null,"Min":null,"Max":null,"Avg":null},{"Variable":"crc_errors","Now":null,"Min":null,"Max":null,"Avg":null},{"Variable":"crc_errors_delta","Now":null,"Min":null,"Max":null,"Avg":null},{"Variable":"crc_errors_hourly","Now":null,"Min":null,"Max":null,"Avg":null},{"Variable":"crc_errors_daily","Now":null,"Min":0.0,"Max":0.0,"Avg":0.0},{"Variable":"valid_packets","Now":null,"Min":null,"Max":null,"Avg":null},{"Variable":"trigger_delta","Now":null,"Min":null,"Max":null,"Avg":null},{"Variable":"trigger_rate_1min","Now":null,"Min":null,"Max":null,"Avg":null},{"Variable":"trigger_rate_5min","Now":null,"Min":null,"Max":null,"Avg":null},{"Variable":"trigger_rate_1hr","Now":null,"Min":null,"Max":null,"Avg":null},{"Variable":"bytes_read","Now":null,"Min":null,"Max":null,"Avg":null},{"Variable":"bytes_written","Now":null,"Min":null,"Max":null,"Avg":null},{"Variable":"bytes_remaining","Now":null,"Min":null,"Max":null,"Avg":null},{"Variable":"triggers_remaining","Now":null,"Min":null,"Max":null,"Avg":null},{"Variable":"packets_sent","Now":null,"Min":null,"Max":null,"Avg":null},{"Variable":"packets_dropped","Now":null,"Min":null,"Max":null,"Avg":null}]