[{"Variable":"runtime","Now":24.33,"Min":0.33,"Max":24.33,"Avg":12.33},{"Variable":"ping","Now":1.0,"Min":0.0,"Max":2.0,"Avg":0.71},{"Variable":"adc_vb_f","Now":14.514,"Min":10.596,"Max":14.85,"Avg":13.07},{"Variable":"adc_va_f","Now":41.977,"Min":10.388,"Max":43.369,"Avg":24.19},{"Variable":"adc_vl_f","Now":14.645,"Min":0.0,"Max":14.975,"Avg":6.12},{"Variable":"adc_ic_f","Now":1.71,"Min":0.0,"Max":2.597,"Avg":0.67},{"Variable":"adc_il_f","Now":1.102,"Min":0.0,"Max":2.181,"Avg":0.5},{"Variable":"t_hs","Now":19.0,"Min":-1.0,"Max":19.0,"Avg":6.48},{"Variable":"t_batt","Now":18.0,"Min":-1.0,"Max":18.0,"Avg":6.24},{"Variable":"t_amb","Now":18.0,"Min":-1.0,"Max":18.0,"Avg":6.24},{"Variable":"t_rts","Now":25.0,"Min":25.0,"Max":25.0,"Avg":25.0},{"Variable":"charge_state","Now":6.0,"Min":1.0,"Max":7.0,"Avg":5.64},{"Variable":"array_fault","Now":0.0,"Min":0.0,"Max":0.0,"Avg":0.0},{"Variable":"vb_f","Now":14.517,"Min":10.687,"Max":14.825,"Avg":13.06},{"Variable":"vb_ref","Now":14.514,"Min":0.0,"Max":14.999,"Avg":14.65},{"Variable":"ahc_r","Now":773.1,"Min":757.1,"Max":773.1,"Avg":765.89},{"Variable":"ahc_t","Now":773.1,"Min":757.1,"Max":773.1,"Avg":765.89},{"Variable":"kwhc","Now":10.6,"Min":10.4,"Max":10.6,"Avg":10.49},{"Variable":"load_state","Now":1.0,"Min":1.0,"Max":3.0,"Avg":2.14},{"Variable":"load_fault","Now":0.0,"Min":0.0,"Max":0.0,"Avg":0.0},{"Variable":"v_lvd","Now":11.499,"Min":11.478,"Max":11.499,"Avg":11.5},{"Variable":"ahl_r","Now":655.1,"Min":643.0,"Max":655.1,"Avg":649.79},{"Variable":"ahl_t","Now":655.1,"Min":643.0,"Max":655.1,"Avg":649.79},{"Variable":"hourmeter","Now":9091.0,"Min":9067.0,"Max":9091.0,"Avg":9078.56},{"Variable":"alarm","Now":1.0,"Min":1.0,"Max":1.0,"Avg":1.0},{"Variable":"dip_switch","Now":1101.0,"Min":1101.0,"Max":1101.0,"Avg":1101.0},{"Variable":"led_state","Now":5.0,"Min":4.0,"Max":11.0,"Avg":8.32},{"Variable":"power_out","Now":23.871,"Min":0.0,"Max":38.335,"Avg":9.44},{"Variable":"power_load","Now":16.139,"Min":0.0,"Max":24.824,"Avg":6.9},{"Variable":"sweep_vmp","Now":37.686,"Min":7.925,"Max":37.686,"Avg":20.89},{"Variable":"sweep_pmax","Now":39.815,"Min":3.684,"Max":39.815,"Avg":16.21},{"Variable":"sweep_voc","Now":43.335,"Min":10.568,"Max":43.335,"Avg":25.25},{"Variable":"vb_min_daily","Now":10.025,"Min":9.875,"Max":12.494,"Avg":9.91},{"Variable":"vb_max_daily","Now":15.051,"Min":12.772,"Max":15.1,"Avg":14.98},{"Variable":"ahc_daily","Now":6.6,"Min":0.0,"Max":16.1,"Avg":12.67},{"Variable":"ahl_daily","Now":4.6,"Min":0.0,"Max":12.0,"Avg":9.18},{"Variable":"array_fault_daily","Now":0.0,"Min":0.0,"Max":0.0,"Avg":0.0},{"Variable":"load_fault_daily","Now":0.0,"Min":0.0,"Max":0.0,"Avg":0.0},{"Variable":"alarm_daily","Now":1e+19,"Min":1e+19,"Max":1e+19,"Avg":1e+19},{"Variable":"vb_min","Now":9.439,"Min":9.439,"Max":9.439,"Avg":9.44},{"Variable":"vb_max","Now":19.47,"Min":19.47,"Max":19.47,"Avg":19.47},{"Variable":"sensor_uptime","Now":0.002,"Min":0.0,"Max":0.018,"Avg":0.01},{"Variable":"crc_errors","Now":0.0,"Min":0.0,"Max":1.0,"Avg":0.0},{"Variable":"crc_errors_delta","Now":0.0,"Min":0.0,"Max":0.0,"Avg":0.0},{"Variable":"crc_errors_hourly","Now":0.0,"Min":0.0,"Max":0.0,"Avg":0.0},{"Variable":"crc_errors_daily","Now":0.0,"Min":0.0,"Max":2.0,"Avg":0.22},{"Variable":"valid_packets","Now":0.0,"Min":0.0,"Max":0.0,"Avg":0.0},{"Variable":"trigger_delta","Now":0.0,"Min":0.0,"Max":0.0,"Avg":0.0},{"Variable":"trigger_rate_1min","Now":0.0,"Min":0.0,"Max":0.0,"Avg":0.0},{"Variable":"trigger_rate_5min","Now":0.0,"Min":0.0,"Max":0.0,"Avg":0.0},{"Variable":"trigger_rate_1hr","Now":0.0,"Min":0.0,"Max":0.0,"Avg":0.0},{"Variable":"bytes_read","Now":0.16,"Min":0.02,"Max":0.18,"Avg":0.15},{"Variable":"bytes_written","Now":0.0,"Min":0.0,"Max":0.0,"Avg":0.0},{"Variable":"bytes_remaining","Now":0.0,"Min":0.0,"Max":0.0,"Avg":0.0},{"Variable":"triggers_remaining","Now":0.0,"Min":0.0,"Max":0.0,"Avg":0.0},{"Variable":"packets_sent","Now":0.0,"Min":0.0,"Max":0.0,"Avg":0.0},{"Variable":"packets_dropped","Now":0.0,"Min":0.0,"Max":0.0,"Avg":0.0}]