[{"Variable":"runtime","Now":110.05,"Min":86.07,"Max":110.05,"Avg":98.06},{"Variable":"ping","Now":0.0,"Min":0.0,"Max":2.0,"Avg":0.99},{"Variable":"adc_vb_f","Now":14.139,"Min":12.643,"Max":14.45,"Avg":13.12},{"Variable":"adc_va_f","Now":36.404,"Min":0.342,"Max":42.908,"Avg":15.31},{"Variable":"adc_vl_f","Now":14.066,"Min":0.0,"Max":14.23,"Avg":0.11},{"Variable":"adc_ic_f","Now":2.45,"Min":0.0,"Max":2.839,"Avg":0.48},{"Variable":"adc_il_f","Now":0.949,"Min":0.0,"Max":1.123,"Avg":0.01},{"Variable":"t_hs","Now":32.0,"Min":16.0,"Max":32.0,"Avg":20.27},{"Variable":"t_batt","Now":30.0,"Min":17.0,"Max":30.0,"Avg":20.43},{"Variable":"t_amb","Now":30.0,"Min":17.0,"Max":30.0,"Avg":20.43},{"Variable":"t_rts","Now":25.0,"Min":25.0,"Max":25.0,"Avg":25.0},{"Variable":"charge_state","Now":6.0,"Min":3.0,"Max":7.0,"Avg":4.31},{"Variable":"array_fault","Now":0.0,"Min":0.0,"Max":0.0,"Avg":0.0},{"Variable":"vb_f","Now":14.139,"Min":12.671,"Max":14.447,"Avg":13.12},{"Variable":"vb_ref","Now":14.148,"Min":0.0,"Max":14.514,"Avg":6.19},{"Variable":"ahc_r","Now":968.6,"Min":957.2,"Max":968.6,"Avg":963.61},{"Variable":"ahc_t","Now":968.6,"Min":957.2,"Max":968.6,"Avg":963.61},{"Variable":"kwhc","Now":13.4,"Min":13.2,"Max":13.4,"Avg":13.31},{"Variable":"load_state","Now":1.0,"Min":1.0,"Max":5.0,"Avg":4.97},{"Variable":"load_fault","Now":0.0,"Min":0.0,"Max":0.0,"Avg":0.0},{"Variable":"v_lvd","Now":11.499,"Min":11.499,"Max":11.499,"Avg":11.5},{"Variable":"ahl_r","Now":795.2,"Min":795.0,"Max":795.2,"Avg":795.0},{"Variable":"ahl_t","Now":795.2,"Min":795.0,"Max":795.2,"Avg":795.0},{"Variable":"hourmeter","Now":8222.0,"Min":8198.0,"Max":8222.0,"Avg":8210.05},{"Variable":"alarm","Now":1.0,"Min":1.0,"Max":1.0,"Avg":1.0},{"Variable":"dip_switch","Now":1101.0,"Min":1101.0,"Max":1101.0,"Avg":1101.0},{"Variable":"led_state","Now":5.0,"Min":5.0,"Max":11.0,"Avg":10.95},{"Variable":"power_out","Now":34.53,"Min":0.0,"Max":40.057,"Avg":6.66},{"Variable":"power_load","Now":13.349,"Min":0.0,"Max":15.731,"Avg":0.1},{"Variable":"sweep_vmp","Now":31.903,"Min":8.127,"Max":32.791,"Avg":17.59},{"Variable":"sweep_pmax","Now":42.08,"Min":4.213,"Max":42.08,"Avg":8.82},{"Variable":"sweep_voc","Now":39.374,"Min":10.837,"Max":40.35,"Avg":22.45},{"Variable":"vb_min_daily","Now":12.643,"Min":12.393,"Max":12.796,"Avg":12.62},{"Variable":"vb_max_daily","Now":14.407,"Min":12.796,"Max":14.673,"Avg":13.51},{"Variable":"ahc_daily","Now":4.6,"Min":0.0,"Max":11.9,"Avg":2.79},{"Variable":"ahl_daily","Now":0.2,"Min":0.0,"Max":0.3,"Avg":0.08},{"Variable":"array_fault_daily","Now":0.0,"Min":0.0,"Max":0.0,"Avg":0.0},{"Variable":"load_fault_daily","Now":0.0,"Min":0.0,"Max":0.0,"Avg":0.0},{"Variable":"alarm_daily","Now":1.0,"Min":1.0,"Max":1.0,"Avg":1.0},{"Variable":"vb_min","Now":9.439,"Min":9.439,"Max":9.439,"Avg":9.44},{"Variable":"vb_max","Now":19.47,"Min":19.47,"Max":19.47,"Avg":19.47},{"Variable":"sensor_uptime","Now":0.171,"Min":0.004,"Max":0.171,"Avg":0.09},{"Variable":"crc_errors","Now":0.0,"Min":0.0,"Max":0.0,"Avg":0.0},{"Variable":"crc_errors_delta","Now":0.0,"Min":0.0,"Max":0.0,"Avg":0.0},{"Variable":"crc_errors_hourly","Now":0.0,"Min":0.0,"Max":0.0,"Avg":0.0},{"Variable":"crc_errors_daily","Now":0.0,"Min":0.0,"Max":0.0,"Avg":0.0},{"Variable":"valid_packets","Now":102.0,"Min":2.0,"Max":102.0,"Avg":52.55},{"Variable":"trigger_delta","Now":8.0,"Min":6.0,"Max":14.0,"Avg":10.0},{"Variable":"trigger_rate_1min","Now":8.0,"Min":6.0,"Max":14.0,"Avg":10.0},{"Variable":"trigger_rate_5min","Now":10.2,"Min":8.8,"Max":11.667,"Avg":10.2},{"Variable":"trigger_rate_1hr","Now":10.0,"Min":9.833,"Max":10.222,"Avg":9.99},{"Variable":"bytes_read","Now":2.31,"Min":0.05,"Max":2.31,"Avg":1.2},{"Variable":"bytes_written","Now":2.24,"Min":0.04,"Max":2.24,"Avg":1.15},{"Variable":"bytes_remaining","Now":431.04,"Min":431.04,"Max":433.24,"Avg":432.13},{"Variable":"triggers_remaining","Now":19593.0,"Min":19593.0,"Max":19693.0,"Avg":19642.36},{"Variable":"packets_sent","Now":0.0,"Min":0.0,"Max":0.0,"Avg":0.0},{"Variable":"packets_dropped","Now":0.0,"Min":0.0,"Max":0.0,"Avg":0.0}]