[{"Variable":"runtime","Now":113.38,"Min":89.38,"Max":113.38,"Avg":101.38},{"Variable":"ping","Now":0.0,"Min":0.0,"Max":2.0,"Avg":0.86},{"Variable":"adc_vb_f","Now":13.123,"Min":12.643,"Max":14.45,"Avg":13.09},{"Variable":"adc_va_f","Now":32.08,"Min":0.342,"Max":42.218,"Avg":15.05},{"Variable":"adc_vl_f","Now":13.205,"Min":0.0,"Max":14.24,"Avg":1.99},{"Variable":"adc_ic_f","Now":1.664,"Min":0.0,"Max":2.839,"Avg":0.55},{"Variable":"adc_il_f","Now":1.276,"Min":0.0,"Max":1.621,"Avg":0.16},{"Variable":"t_hs","Now":30.0,"Min":16.0,"Max":33.0,"Avg":21.41},{"Variable":"t_batt","Now":28.0,"Min":17.0,"Max":32.0,"Avg":21.41},{"Variable":"t_amb","Now":28.0,"Min":17.0,"Max":32.0,"Avg":21.41},{"Variable":"t_rts","Now":25.0,"Min":25.0,"Max":25.0,"Avg":25.0},{"Variable":"charge_state","Now":7.0,"Min":3.0,"Max":7.0,"Avg":4.29},{"Variable":"array_fault","Now":0.0,"Min":0.0,"Max":0.0,"Avg":0.0},{"Variable":"vb_f","Now":13.177,"Min":12.671,"Max":14.447,"Avg":13.09},{"Variable":"vb_ref","Now":13.608,"Min":0.0,"Max":14.514,"Avg":6.18},{"Variable":"ahc_r","Now":975.2,"Min":962.1,"Max":975.2,"Avg":965.33},{"Variable":"ahc_t","Now":975.2,"Min":962.1,"Max":975.2,"Avg":965.33},{"Variable":"kwhc","Now":13.5,"Min":13.3,"Max":13.5,"Avg":13.33},{"Variable":"load_state","Now":1.0,"Min":1.0,"Max":5.0,"Avg":4.41},{"Variable":"load_fault","Now":0.0,"Min":0.0,"Max":0.0,"Avg":0.0},{"Variable":"v_lvd","Now":11.499,"Min":11.499,"Max":11.499,"Avg":11.5},{"Variable":"ahl_r","Now":798.8,"Min":795.0,"Max":798.8,"Avg":795.27},{"Variable":"ahl_t","Now":798.8,"Min":795.0,"Max":798.8,"Avg":795.27},{"Variable":"hourmeter","Now":8225.0,"Min":8201.0,"Max":8225.0,"Avg":8213.37},{"Variable":"alarm","Now":1.0,"Min":1.0,"Max":1.0,"Avg":1.0},{"Variable":"dip_switch","Now":1101.0,"Min":1101.0,"Max":1101.0,"Avg":1101.0},{"Variable":"led_state","Now":4.0,"Min":4.0,"Max":11.0,"Avg":10.01},{"Variable":"power_out","Now":21.908,"Min":0.0,"Max":40.117,"Avg":7.59},{"Variable":"power_load","Now":16.85,"Min":0.0,"Max":20.677,"Avg":2.18},{"Variable":"sweep_vmp","Now":32.126,"Min":8.127,"Max":32.394,"Avg":17.43},{"Variable":"sweep_pmax","Now":22.844,"Min":4.213,"Max":42.08,"Avg":11.0},{"Variable":"sweep_voc","Now":38.782,"Min":10.837,"Max":39.868,"Avg":22.32},{"Variable":"vb_min_daily","Now":12.488,"Min":12.393,"Max":12.796,"Avg":12.65},{"Variable":"vb_max_daily","Now":14.407,"Min":12.796,"Max":14.673,"Avg":13.47},{"Variable":"ahc_daily","Now":11.2,"Min":0.0,"Max":11.9,"Avg":2.86},{"Variable":"ahl_daily","Now":3.8,"Min":0.0,"Max":3.8,"Avg":0.31},{"Variable":"array_fault_daily","Now":0.0,"Min":0.0,"Max":0.0,"Avg":0.0},{"Variable":"load_fault_daily","Now":0.0,"Min":0.0,"Max":0.0,"Avg":0.0},{"Variable":"alarm_daily","Now":1.0,"Min":1.0,"Max":1.0,"Avg":1.0},{"Variable":"vb_min","Now":9.439,"Min":9.439,"Max":9.439,"Avg":9.44},{"Variable":"vb_max","Now":19.47,"Min":19.47,"Max":19.47,"Avg":19.47},{"Variable":"sensor_uptime","Now":2.538,"Min":0.004,"Max":2.538,"Avg":1.05},{"Variable":"crc_errors","Now":2.0,"Min":0.0,"Max":2.0,"Avg":1.46},{"Variable":"crc_errors_delta","Now":0.0,"Min":0.0,"Max":0.0,"Avg":0.0},{"Variable":"crc_errors_hourly","Now":0.0,"Min":0.0,"Max":0.0,"Avg":0.0},{"Variable":"crc_errors_daily","Now":0.0,"Min":0.0,"Max":0.0,"Avg":0.0},{"Variable":"valid_packets","Now":1936.0,"Min":2.0,"Max":1936.0,"Avg":720.84},{"Variable":"trigger_delta","Now":16.0,"Min":5.0,"Max":24.0,"Avg":11.94},{"Variable":"trigger_rate_1min","Now":16.0,"Min":5.0,"Max":24.0,"Avg":11.94},{"Variable":"trigger_rate_5min","Now":14.8,"Min":7.8,"Max":19.2,"Avg":11.9},{"Variable":"trigger_rate_1hr","Now":15.217,"Min":9.375,"Max":15.217,"Avg":11.16},{"Variable":"bytes_read","Now":43.63,"Min":0.05,"Max":43.63,"Avg":16.32},{"Variable":"bytes_written","Now":42.59,"Min":0.04,"Max":42.59,"Avg":15.86},{"Variable":"bytes_remaining","Now":378.53,"Min":378.53,"Max":433.24,"Avg":408.57},{"Variable":"triggers_remaining","Now":17206.0,"Min":17206.0,"Max":19693.0,"Avg":18571.24},{"Variable":"packets_sent","Now":0.0,"Min":0.0,"Max":0.0,"Avg":0.0},{"Variable":"packets_dropped","Now":0.0,"Min":0.0,"Max":0.0,"Avg":0.0}]